argpass/__init__.py
argpass/argpass.py
argpass/py.typed
argpass-0.0.2.dist-info/METADATA
argpass-0.0.2.dist-info/WHEEL
argpass-0.0.2.dist-info/top_level.txt
argpass-0.0.2.dist-info/RECORD
