Metadata-Version: 2.1
Name: argpass
Version: 0.0.2
Summary: An extension of argparse to facilitate passing on arguments to other programs
Home-page: https://github.com/julibeg/argpass
License: Public Domain
Platform: UNKNOWN
Classifier: Programming Language :: Python :: 3
Classifier: Programming Language :: Python :: 3.6
Classifier: Programming Language :: Python :: 3.7
Classifier: Programming Language :: Python :: 3.8
Classifier: Programming Language :: Python :: 3.9
Classifier: Programming Language :: Python :: 3.10
Requires-Python: >=3.6
Provides-Extra: testing
